endstone_pluggy/__init__.py
endstone_pluggy/pluggy.py
endstone_pluggy-0.1.1.dist-info/METADATA
endstone_pluggy-0.1.1.dist-info/WHEEL
endstone_pluggy-0.1.1.dist-info/entry_points.txt
endstone_pluggy-0.1.1.dist-info/licenses/LICENSE
endstone_pluggy-0.1.1.dist-info/RECORD
