Metadata-Version: 2.3
Name: endstone-pluggy
Version: 0.1.1
Summary: Python plugin and permission manager for endstone
Author: Cryotap
License:                     GNU GENERAL PUBLIC LICENSE
License-File: LICENSE
Keywords: endstone,manager,permission manager,plugin,plugin manager
